Workbook

Sheet Transactions
A1: LA FISSURE — Bilan des dépenses et revenus
A2: JAXA Production Inc. · Compte 2-21 La Fissure · Phase Concept
A3: Document généré le 2026-05-27 — destiné au comptable
A5: Date | B5: N° pièce | C5: Type | D5: Description | E5: Catégorie | F5: Fournisseur / Client | G5: Compte bancaire | H5: Revenus HT | I5: Dépenses HT | J5: TPS (5 %) | K5: TVQ (9,975 %) | L5: Total TTC | M5: Mode de paiement
A6: 46169 | B6: 46152 | C6: dépense | D6: 05-010 Remboursement Surplus - Transfert versCpte 20 | G6: Compte 2-21 La Fissure | I6: 25.18 | L6: =N(H6)+N(I6)+N(J6)+N(K6) -> 25.18 | M6: Dépôt direct
A7: 46169 | B7: 46148 | C7: revenu | D7: 05-06 Remboursement Part Productrice - Transfert du Cpte 20 | F7: JAXA - Cpte PROD 20 | G7: Compte 2-21 La Fissure | H7: 845.07 | L7: =N(H7)+N(I7)+N(J7)+N(K7) -> 845.07 | M7: Dépôt direct
A8: 46169 | B8: 05-07 | C8: dépense | D8: 05-07 Fabio Pellegrino — Storyboard - Conceptualisation pour le projet La Fissure | E8: Services professionnels | F8: Fabio Pellegrino | G8: Compte 2-21 La Fissure | I8: 1500 | J8: 75 | K8: 149.63 | L8: =N(H8)+N(I8)+N(J8)+N(K8) -> 1724.63 | M8: Dépôt direct
A9: 46169 | B9: 05-06 | C9: dépense | D9: 05-06 Facture FIS-ServicePro_Invest_FIS-052926 — JAXA - Production La Fissure | E9: Services professionnels | F9: JAXA - Production La Fissure | G9: Compte 2-21 La Fissure | I9: 735 | J9: 0 | K9: 0 | L9: =N(H9)+N(I9)+N(J9)+N(K9) -> 735 | M9: Virement Interac
A10: 46168 | B10: 05-03 | C10: dépense | D10: 05-03 Couleur Point TV Inc. — Services de conceptualisation et direction artistique - LAFISSURE | E10: Services professionnels | F10: Couleur.tv | G10: Compte 2-21 La Fissure | I10: 3064 | J10: 153.2 | K10: 305.64 | L10: =N(H10)+N(I10)+N(J10)+N(K10) -> 3522.84 | M10: Dépôt direct
A11: 46167 | B11: 05-05 | C11: dépense | D11: 05-05 Axelle Michaud — Coordination de projet - La Fissure | E11: Services professionnels | F11: Axelle Michaud | G11: Compte 2-21 La Fissure | I11: 500 | L11: =N(H11)+N(I11)+N(J11)+N(K11) -> 500 | M11: Virement Interac
A12: 46142 | B12: 04-04 | C12: dépense | D12: 04-04 Frais bancaires — Compte 2-21 La Fissure | E12: Frais bancaires | G12: Compte 2-21 La Fissure | I12: 7 | L12: =N(H12)+N(I12)+N(J12)+N(K12) -> 7 | M12: Débit
A13: 46112 | B13: 03-01 | C13: dépense | D13: 03-01 Frais bancaires — Compte 2-21 La Fissure - FRAIS Forfait | E13: Frais bancaires | G13: Compte 2-21 La Fissure | I13: 7 | L13: =N(H13)+N(I13)+N(J13)+N(K13) -> 7 | M13: Dépôt direct
A14: 46080 | B14: 02-02 | C14: dépense | D14: 02-02 Frais bancaires — Compte 2-21 La Fissure | E14: Frais bancaires | G14: Compte 2-21 La Fissure | I14: 7 | L14: =N(H14)+N(I14)+N(J14)+N(K14) -> 7 | M14: Débit
A15: 46064 | B15: 02-01 | C15: dépense | D15: 02-01_F-Roque - Poste 10.15_Projet Fissure | E15: Services professionnels | F15: Felix Rocque | G15: Compte 2-21 La Fissure | I15: 2000 | J15: 100 | K15: 199.5 | L15: =N(H15)+N(I15)+N(J15)+N(K15) -> 2299.5 | M15: Dépôt direct
A16: 46052 | B16: 01-01 | C16: dépense | D16: 01-01 Frais bancaires — Compte 2-21 La Fissure | E16: Frais bancaires | G16: Compte 2-21 La Fissure | I16: 7 | L16: =N(H16)+N(I16)+N(J16)+N(K16) -> 7 | M16: Débit
A17: 46022 | B17: 12-01 | C17: dépense | D17: 12-01 Frais bancaires — Compte 2-21 La Fissure | E17: Frais bancaires | G17: Compte 2-21 La Fissure | I17: 7 | L17: =N(H17)+N(I17)+N(J17)+N(K17) -> 7 | M17: Débit
A18: 45989 | B18: 11-02 | C18: dépense | D18: 11-02 Frais bancaires — Compte 2-21 La Fissure - FRAIS FORFAIT | E18: Frais bancaires | F18: JAXA - Cpte PROD 21 | G18: Compte 2-21 La Fissure | I18: 7 | L18: =N(H18)+N(I18)+N(J18)+N(K18) -> 7 | M18: Débit
A19: 45981 | B19: 11-01 | C19: revenu | D19: 11-01 CPTE DEBITEUR - CANADA MEDIA FOUND // 11-01-FIS_Contrat_FMC | E19: Revenu client | F19: Fonds Media du Canada - FMC | G19: Compte 2-21 La Fissure | H19: 7919 | L19: =N(H19)+N(I19)+N(J19)+N(K19) -> 7919 | M19: Dépôt direct
A20: 45961 | B20: 10-03 | C20: dépense | D20: 10-03 Frais bancaires — Compte 2-21 La Fissure | E20: Frais bancaires | G20: Compte 2-21 La Fissure | I20: 0.03 | L20: =N(H20)+N(I20)+N(J20)+N(K20) -> 0.03 | M20: Débit
A21: 45961 | B21: 46297 | C21: dépense | D21: 11-02 Frais bancaires — Compte 2-21 La Fissure - FRAIS FORFAIT | E21: Frais bancaires | F21: JAXA - Cpte PROD 21 | G21: Compte 2-21 La Fissure | I21: 7 | L21: =N(H21)+N(I21)+N(J21)+N(K21) -> 7 | M21: Débit
A22: 45940 | B22: 46296 | C22: revenu | D22: 10-01 Prêt - Transfert du Cpte 20 | E22: Revenu client | F22: JAXA - Cpte PROD 20 | G22: Compte 2-21 La Fissure | H22: 20 | L22: =N(H22)+N(I22)+N(J22)+N(K22) -> 20 | M22: Dépôt direct
A23: 45929 | B23: 09-02 | C23: dépense | D23: 09-02 Frais bancaires — Compte 2-21 La Fissure | E23: Frais bancaires | G23: Compte 2-21 La Fissure | I23: 0.01 | L23: =N(H23)+N(I23)+N(J23)+N(K23) -> 0.01 | M23: Débit
A24: 45929 | B24: 46266 | C24: dépense | D24: 09-01 Frais bancaires — Compte 2-21 La Fissure | E24: Frais bancaires | G24: Compte 2-21 La Fissure | I24: 6.07 | L24: =N(H24)+N(I24)+N(J24)+N(K24) -> 6.07 | M24: Débit
A26: SOUS-TOTAL DÉPENSES | I26: =SUMIF(C6:C24,"dépense",I6:I24) -> 7879.29 | J26: =SUMIFS(J8:J24,C8:C24,"dépense") -> 328.2 | K26: =SUMIFS(K8:K24,C8:C24,"dépense") -> 654.77 | L26: =SUMIFS(L6:L24,C6:C24,"dépense") -> 8862.26
A27: SOUS-TOTAL REVENUS | H27: =SUMIFS(H6:H24,C6:C24,"revenu") -> 8784.07 | J27: =SUMIFS(J8:J24,C8:C24,"revenu") -> 0 | K27: =SUMIFS(K8:K24,C8:C24,"revenu") -> 0 | L27: =SUMIFS(L8:L24,C8:C24,"revenu") -> 7939
A29: SOLDE NET (Revenus − Dépenses) | H29: =H27-I26 -> 904.78 | L29: =L27-L26 -> -923.26

Sheet Sommaire comptable
A1: Sommaire comptable — La Fissure
A2: Période couverte : voir feuille Transactions · Compte 2-21 La Fissure
B4: 1. Résultats — Hors taxes
B5: Total des revenus (HT) | C5: =Transactions!H27 -> 8784.07 | D5: Subventions et autres entrées avant taxes
B6: Total des dépenses (HT) | C6: =Transactions!I26 -> 7879.29 | D6: Achats et services avant taxes
B7: SOLDE NET (HT) | C7: =Transactions!H27-Transactions!I26 -> 904.78 | D7: Revenus HT − Dépenses HT
B9: 2. Taxes — Crédits récupérables
B10: TPS payée sur dépenses (CTI — crédit fédéral) | C10: =Transactions!J26 -> 328.2 | D10: À récupérer auprès de l’ARC
B11: TVQ payée sur dépenses (RTI — crédit provincial) | C11: =Transactions!K26 -> 654.77 | D11: À récupérer auprès de Revenu Québec
B12: Total des crédits de taxes à récupérer | C12: =Transactions!J26+Transactions!K26 -> 982.97
B14: 3. Taxes — Perçues sur revenus
B15: TPS perçue sur revenus | C15: =Transactions!J27 -> 0 | D15: À remettre à l’ARC (le cas échéant)
B16: TVQ perçue sur revenus | C16: =Transactions!K27 -> 0 | D16: À remettre à Revenu Québec (le cas échéant)
B18: 4. Position nette de taxes
B19: TPS nette (perçue − payée) | C19: =Transactions!J27-Transactions!J26 -> -328.2 | D19: Négatif = remboursement attendu de l’ARC
B20: TVQ nette (perçue − payée) | C20: =Transactions!K27-Transactions!K26 -> -654.77 | D20: Négatif = remboursement attendu de Revenu Québec
B22: 5. Mouvements de trésorerie (TTC)
B23: Total des entrées (revenus TTC) | C23: =Transactions!L27 -> 7939
B24: Total des sorties (dépenses TTC) | C24: =Transactions!L26 -> 8862.26
B25: Variation nette de trésorerie | C25: =Transactions!L27-Transactions!L26 -> -923.26
B28: Note : Tous les montants sont reliés par formules à la feuille « Transactions ». Toute modification dans la feuille Transactions met automatiquement à jour ce sommaire.

Sheet Par catégorie
A1: Ventilation par catégorie comptable
A2: Pour faciliter les écritures dans le grand livre
A4: Catégorie | B4: Type | C4: Montant HT | D4: TPS | E4: TVQ | F4: Total TTC
A5: Frais bancaires | B5: dépense | C5: =SUMIFS(Transactions!I8:I24,Transactions!E8:E24,A5,Transactions!C8:C24,"dépense") -> 55.11 | D5: =SUMIFS(Transactions!J8:J24,Transactions!E8:E24,A5,Transactions!C8:C24,"dépense") -> 0 | E5: =SUMIFS(Transactions!K8:K24,Transactions!E8:E24,A5,Transactions!C8:C24,"dépense") -> 0 | F5: =C5+D5+E5 -> 55.11
A6: Services professionnels | B6: dépense | C6: =SUMIFS(Transactions!I8:I24,Transactions!E8:E24,A6,Transactions!C8:C24,"dépense") -> 7799 | D6: =SUMIFS(Transactions!J8:J24,Transactions!E8:E24,A6,Transactions!C8:C24,"dépense") -> 328.2 | E6: =SUMIFS(Transactions!K8:K24,Transactions!E8:E24,A6,Transactions!C8:C24,"dépense") -> 654.77 | F6: =C6+D6+E6 -> 8781.97
A7: Revenu client | B7: revenu | C7: =SUMIFS(Transactions!H8:H24,Transactions!E8:E24,A7,Transactions!C8:C24,"revenu") -> 7939 | D7: =SUMIFS(Transactions!J8:J24,Transactions!E8:E24,A7,Transactions!C8:C24,"revenu") -> 0 | E7: =SUMIFS(Transactions!K8:K24,Transactions!E8:E24,A7,Transactions!C8:C24,"revenu") -> 0 | F7: =C7+D7+E7 -> 7939
A9: TOTAL | C9: =SUM(C5:C7) -> 15793.11 | D9: =SUM(D5:D7) -> 328.2 | E9: =SUM(E5:E7) -> 654.77 | F9: =SUM(F5:F7) -> 16776.08
